setup.cfg
setup.py
fi_an225/__init__.py
fi_an225.egg-info/PKG-INFO
fi_an225.egg-info/SOURCES.txt
fi_an225.egg-info/dependency_links.txt
fi_an225.egg-info/not-zip-safe
fi_an225.egg-info/top_level.txt
fi_an225/circle/__init__.py
fi_an225/circle/code.py
fi_an225/square/__init__.py
fi_an225/square/code.py
fi_an225/triangle/__init__.py
fi_an225/triangle/code.py