Metadata-Version: 2.1
Name: fi-an225
Version: 0.1
Summary: circle, tiangle, square
Author-email: alexeykozhakin@gmail.com
